aec6s/AEC.py
aec6s/__init__.py
aec6s/anci_download.py
aec6s/anci_get_AER.py
aec6s/anci_get_OWV.py
aec6s/anci_list_files.py
aec6s/fillnan.py
aec6s/get_ancillary.py
aec6s/get_parameters.py
aec6s/read_metadata.py
aec6s/run.py
aec6s-1.0.1.dist-info/LICENSE
aec6s-1.0.1.dist-info/METADATA
aec6s-1.0.1.dist-info/WHEEL
aec6s-1.0.1.dist-info/top_level.txt
aec6s-1.0.1.dist-info/RECORD
